hurnet_torch/__init__.py
hurnet_torch/_activation_functions.py
hurnet_torch/_device_detection.py
hurnet_torch/_hurnet_torch.py
hurnet_torch/_hurnet_transformer.py
hurnet_torch/_transformer_hurnet.py
hurnet_torch/hurnet_torch.py
hurnet_torch-1.1.0.dist-info/LICENSE.txt
hurnet_torch-1.1.0.dist-info/METADATA
hurnet_torch-1.1.0.dist-info/WHEEL
hurnet_torch-1.1.0.dist-info/top_level.txt
hurnet_torch-1.1.0.dist-info/RECORD
