Metadata-Version: 2.2
Name: hurnet_torch
Version: 1.1.0
Home-page: https://github.com/sapiens-technology/HurNetTorch
Author: SAPIENS TECHNOLOGY
License: Proprietary Software
License-File: LICENSE.txt
Requires-Dist: torch
Requires-Dist: numpy
Requires-Dist: tqdm
Dynamic: author
Dynamic: home-page
Dynamic: license
Dynamic: requires-dist
